{
    "id": "2003_as_core_ipv4",
    "name": "2003 AS Core: IPv4",
    "description": "1,134,634 IP addresses, 2,434,073 IP links, 865,000 destinations, 62% of globally routable network prefixes; 11,411 ASes (73% of ASes present in RouteViews BGP tables on May 8, 2003), 32,209 peering sessions.",
    "tags":[
        "caida",
        "skitter",
        "ipv4",
        "routed 24",
        "as2prefix", 
        "poster",
        "as_core"
    ],
    "links":[
        {"to":"dataset:skitter_internet_topology_data_kit"},
        {"to":"dataset:as_prefix"},
        {"to":"dataset:ipv4_routed_24_topology"}
    ],
    "date":"2003.04",
    "type":"POSTER",
    "resources":[
        {
            "name":"PNG IPv4",
            "url":"https://www.caida.org/research/topology/as_core_network/pics/ascore-2003-apr-ipv4-standalone-1600x1333.png"
        }
    ],
    "authors":[]
}
