{
    "id": "geoplot",
    "name": "GeoPlot",
    "organization": "CAIDA",
    "description": "GeoPlot is a light-weight java applet which allows users to create a geographical image of a data set. The applet provides the user with many options to represent the data set. Basically, GeoPlot plots a set of nodes and a set of lines that connect these nodes on an image specified by the user.",
    "tags": [
        "visualization",
        "topology",
        "caida"
    ],
    "dateStart": "1999.07",
    "resources": [
        {
            "name": "public",
            "url": "https://www.caida.org/tools/visualization/geoplot/",
            "tags": [
                "file"
            ]
        }
    ]
}